Workbook
Name GRADES: [1]Sheet1!$H$18:$I$25
Name GRADES2: [1]Sheet1!#REF!
Name GRADES2: [1]Sheet1!#REF!
Name Order_Month: [1]Orders!#REF!
Name Order_Month: [1]Orders!#REF!
Name Order_No: [1]Orders!$A$6:$A$1044
Name Order_Priority: [1]Orders!$J$6:$J$1044
Name Ship_Date: [1]Orders!$O$6:$O$1044
Name Ship_Time: [1]Orders!#REF!
Name Ship_Time: [1]Orders!#REF!
Name Slicer_Branch: #N/A
Name Slicer_Class: #N/A
Name Slicer_G._Segment: #N/A
Name Slicer_Sub_category: #N/A

Sheet Info
A1: Based on the given data Find
A4: 1 | B4: Use Data-1 Sheet:
A5: 2 | B5: ToTal sales | C5: =SUM('Data-1'!J2:J2000) -> 457750.18
A6: 3 | B6: Total Profit | C6: =SUM('Data-1'!M2:M2000) -> 43208.147
A7: 4 | B7: No of Quentity | C7: =SUM('Data-1'!K2:K2000) -> 7571
A8: 5 | B8: Profit after Discount | C8: Look at Data-1 sheet
A9: 6 | B9: Second High Sales | C9: =LARGE(_xlfn.UNIQUE('Data-1'!J2:J2000),2) -> 7999.98
A10: 7 | B10: Fourth Low Sales | C10: =SMALL(_xlfn.UNIQUE('Data-1'!J2:J2000),4) -> 1.188
A11: 8 | B11: Max Profit | C11: =MAX('Data-1'!N2:N2000) -> 3177.475
A12: 9 | B12: Total High Sales>3000 | C12: =SUMIF('Data-1'!J2:J2000,">3000") -> 62777.238
A13: 10 | B13: No of High Sales | C13: =COUNTIF('Data-1'!J2:J2000,">3000") -> 14
A14: 11 | B14: IF New Price = 150 Find New Sales | C14: Look at Data-1 sheet
A15: 12 | B15: Give Those classes to New Sales as Following
B16: Look at Data-1 sheet | C16: A | D16: 2000 | E16: D | F16: 100
C17: B | D17: 1000 | E17: E | F17: less than 100
C18: C | D18: 500
A19: 13 | B19: Average of Top 3 Profit Value | C19: =AVERAGE(LARGE(_xlfn.UNIQUE('Data-1'!M2:M2000),3)) -> 1995.99
A20: 14 | B20: Max new sales | C20: =MAX('Data-1'!O2:O2000) -> 2100
A21: 15 | B21: Min new sales | C21: =MIN('Data-1'!O2:O2000) -> 150
A22: 16 | B22: average new sales | C22: =AVERAGE('Data-1'!O2:O2000) -> 568.10905
A23: 17 | B23: Find Total New sales If State = California | C23: =SUMIF('Data-1'!E2:E2000,"California",'Data-1'!O2:O2000) -> 213300
A24: 18 | B24: Find Average New Sales If state = Texas | C24: =SUMIF('Data-1'!E2:E2000,"Texas",'Data-1'!O2:O2000) -> 113400
A25: 19 | B25: Highlight All Sub Category = Phones ( using Custom Format) | C25: Look at Data-1 sheet
A26: 20 | B26: Highlight all Negative Values in Profit | C26: Look at Data-1 sheet
B27: Based on Sales sheet:
A28: 21 | B28: Establish Relationships Between Tables
B29: Use the Power Pivot data model to import the Sales, Classes, Branches, and Segments tables. Establish relationships between these tables based on the following keys
B30: Class Code (from Sales to Classes table),Sub category code(from Sales to Sub categories table), Branch Code (from Sales to Branches table), Segment Code (from Sales to Segments table).
B31: use Piviot Table to Find:
C32: Avgerage Profit by branch | D32: Look at Pivot Table sheet
C33: sum of profit by branch and segment | D33: Look at Pivot Table sheet
A34: 23 | C34: Calculate discount by 5% on profit | D34: Look at Power Pivot sheet
C35: profit by classes and sub category | D35: Look at Pivot Table sheet
C36: insert slicer for each piviot | D36: Look at Dashboard sheet
C37: insert piviot chart for all piviots and link them together | D37: Look at Dashboard sheet
A38: 24 | B38: Use the data in sales sheet to analyze and convert all necessary data to chart from your own perspective | C38: Look at Dashboard sheet
A39: 25 | B39: Create your Detailed interactive dashboard Based on analyzed data in NO (24) | C39: Look at Dashboard sheet

Sheet Data-1
A1: Row ID | B1: Ship Mode | C1: Segment | D1: City | E1: State | F1: Region | G1: Category | H1: Sub-Category | I1: Product Name | J1: Sales | K1: Quantity | L1: Discount | M1: Profit | N1: Profit after Discount | O1: New Sales | P1: Classes
A2: 1 | B2: Second Class | C2: Consumer | D2: Henderson | E2: Kentucky | F2: South | G2: Furniture | H2: Bookcases | I2: Bush Somerset Collection Bookcase | J2: 261.96 | K2: 2 | L2: 0 | M2: 41.9136 | N2: =M2-(J2*L2) -> 41.9136 | O2: =150*K2 -> 300 | P2: {=_xlfn.IFS(O2>=2000,"A",O2>=1000,"B",O2>=500,"C",O2>=100,"D",O2<100,"E")} -> D
A3: 2 | B3: Second Class | C3: Consumer | D3: Henderson | E3: Kentucky | F3: South | G3: Furniture | H3: Chairs | I3: Hon Deluxe Fabric Upholstered Stacking Chairs, Rounded Back | J3: 731.94 | K3: 3 | L3: 0 | M3: 219.582 | N3: =M3-(J3*L3) -> 219.582 | O3: =150*K3 -> 450 | P3: {=_xlfn.IFS(O3>=2000,"A",O3>=1000,"B",O3>=500,"C",O3>=100,"D",O3<100,"E")} -> D
A4: 3 | B4: Second Class | C4: Corporate | D4: Los Angeles | E4: California | F4: West | G4: Office Supplies | H4: Labels | I4: Self-Adhesive Address Labels for Typewriters by Universal | J4: 11.69 | K4: 2 | L4: 0 | M4: 6.8714 | N4: =M4-(J4*L4) -> 6.8714 | O4: =150*K4 -> 300 | P4: {=_xlfn.IFS(O4>=2000,"A",O4>=1000,"B",O4>=500,"C",O4>=100,"D",O4<100,"E")} -> D
A5: 4 | B5: Standard Class | C5: Consumer | D5: Fort Lauderdale | E5: Florida | F5: South | G5: Furniture | H5: Tables | I5: Bretford CR4500 Series Slim Rectangular Table | J5: 957.5775 | K5: 5 | L5: 0.45 | M5: -383.031 | N5: =M5-(J5*L5) -> -813.94088 | O5: =150*K5 -> 750 | P5: {=_xlfn.IFS(O5>=2000,"A",O5>=1000,"B",O5>=500,"C",O5>=100,"D",O5<100,"E")} -> C
A6: 5 | B6: Standard Class | C6: Consumer | D6: Fort Lauderdale | E6: Florida | F6: South | G6: Office Supplies | H6: Storage | I6: Eldon Fold 'N Roll Cart System | J6: 22.368 | K6: 2 | L6: 0.2 | M6: 2.5164 | N6: =M6-(J6*L6) -> -1.9572 | O6: =150*K6 -> 300 | P6: {=_xlfn.IFS(O6>=2000,"A",O6>=1000,"B",O6>=500,"C",O6>=100,"D",O6<100,"E")} -> D
A7: 6 | B7: Standard Class | C7: Consumer | D7: Los Angeles | E7: California | F7: West | G7: Furniture | H7: Furnishings | I7: Eldon Expressions Wood and Plastic Desk Accessories, Cherry Wood | J7: 48.86 | K7: 7 | L7: 0 | M7: 14.1694 | N7: =M7-(J7*L7) -> 14.1694 | O7: =150*K7 -> 1050 | P7: {=_xlfn.IFS(O7>=2000,"A",O7>=1000,"B",O7>=500,"C",O7>=100,"D",O7<100,"E")} -> B
A8: 7 | B8: Standard Class | C8: Consumer | D8: Los Angeles | E8: California | F8: West | G8: Office Supplies | H8: Art | I8: Newell 322 | J8: 7.28 | K8: 4 | L8: 0 | M8: 1.9656 | N8: =M8-(J8*L8) -> 1.9656 | O8: =150*K8 -> 600 | P8: {=_xlfn.IFS(O8>=2000,"A",O8>=1000,"B",O8>=500,"C",O8>=100,"D",O8<100,"E")} -> C
A9: 8 | B9: Standard Class | C9: Consumer | D9: Los Angeles | E9: California | F9: West | G9: Technology | H9: Phones | I9: Mitel 5320 IP Phone VoIP phone | J9: 907.152 | K9: 6 | L9: 0.2 | M9: 90.7152 | N9: =M9-(J9*L9) -> -90.7152 | O9: =150*K9 -> 900 | P9: {=_xlfn.IFS(O9>=2000,"A",O9>=1000,"B",O9>=500,"C",O9>=100,"D",O9<100,"E")} -> C
A10: 9 | B10: Standard Class | C10: Consumer | D10: Los Angeles | E10: California | F10: West | G10: Office Supplies | H10: Binders | I10: DXL Angle-View Binders with Locking Rings by Samsill | J10: 18.504 | K10: 3 | L10: 0.2 | M10: 5.7825 | N10: =M10-(J10*L10) -> 2.0817 | O10: =150*K10 -> 450 | P10: {=_xlfn.IFS(O10>=2000,"A",O10>=1000,"B",O10>=500,"C",O10>=100,"D",O10<100,"E")} -> D
A11: 10 | B11: Standard Class | C11: Consumer | D11: Los Angeles | E11: California | F11: West | G11: Office Supplies | H11: Appliances | I11: Belkin F5C206VTEL 6 Outlet Surge | J11: 114.9 | K11: 5 | L11: 0 | M11: 34.47 | N11: =M11-(J11*L11) -> 34.47 | O11: =150*K11 -> 750 | P11: {=_xlfn.IFS(O11>=2000,"A",O11>=1000,"B",O11>=500,"C",O11>=100,"D",O11<100,"E")} -> C
A12: 11 | B12: Standard Class | C12: Consumer | D12: Los Angeles | E12: California | F12: West | G12: Furniture | H12: Tables | I12: Chromcraft Rectangular Conference Tables | J12: 1706.184 | K12: 9 | L12: 0.2 | M12: 85.3092 | N12: =M12-(J12*L12) -> -255.9276 | O12: =150*K12 -> 1350 | P12: {=_xlfn.IFS(O12>=2000,"A",O12>=1000,"B",O12>=500,"C",O12>=100,"D",O12<100,"E")} -> B
A13: 12 | B13: Standard Class | C13: Consumer | D13: Los Angeles | E13: California | F13: West | G13: Technology | H13: Phones | I13: Konftel 250 Conference phone - Charcoal black | J13: 911.424 | K13: 4 | L13: 0.2 | M13: 68.3568 | N13: =M13-(J13*L13) -> -113.928 | O13: =150*K13 -> 600 | P13: {=_xlfn.IFS(O13>=2000,"A",O13>=1000,"B",O13>=500,"C",O13>=100,"D",O13<100,"E")} -> C
... A2000: 1999 | B2000: First Class | C2000: Corporate | D2000: Chesapeake | E2000: Virginia | F2000: South | G2000: Technology | H2000: Phones | I2000: Aastra 57i VoIP phone | J2000: 161.61 | K2000: 1 | L2000: 0 | M2000: 42.0186 | N2000: =M2000-(J2000*L2000) -> 42.0186 | O2000: =150*K2000 -> 150 | P2000: {=_xlfn.IFS(O2000>=2000,"A",O2000>=1000,"B",O2000>=500,"C",O2000>=100,"D",O2000<100,"E")} -> D

Sheet Dashboard

Sheet Pivot Table
A1: Branch | B1: Average of Profit | D1: Segment | E1: Sum of Profit | G1: Sub category | H1: Sum of Profit
A2: Marasa Matrouh | B2: 3620.5814 | D2: Canal | G2: Smartphones
A3: Ismailia | B3: 3596.4126 | D3: Portsaied | E3: 1135566 | G3: Apple iPhone | H3: 3320766
A4: Portsaied | B4: 3537.5888 | D4: Ismailia | E4: 1028574 | G4: HTC | H4: 1014102
A5: Aswan | B5: 3486.5415 | D5: Alexandria | G5: Nokia | H5: 332355
A6: Mansoura | B6: 3451.44 | D6: Marasa Matrouh | E6: 1089795 | G6: Samsung | H6: 2750958
A7: Giza | B7: 3395.5585 | D7: Alex | E7: 997830 | G7: Tablets
A8: Cairo | B8: 3384.0604 | D8: Delta | G8: Microsoft | H8: 1322244
A9: Zagazig | B9: 3326.7752 | D9: Mansoura | E9: 1035432 | G9: Samsung | H9: 788544
A10: Alex | B10: 3326.1 | D10: Zagazig | E10: 1021320 | G10: Sony | H10: 718488
A11: Minia | B11: 3052.881 | D11: G. Cairo | G11: Grand Total | H11: 10247457
A12: Grand Total | B12: 3415.819 | D12: Giza | E12: 1015272
D13: Cairo | E13: 1008450 | G13: Sum of Sales
A14: Class | B14: Sum of Profit | D14: Upper Egypt | G14: 160073913
A15: Smartphones | B15: 7418181 | D15: Aswan | E15: 965772
A16: Tablets | B16: 2829276 | D16: Minia | E16: 949446 | G16: Sum of Profit
A17: Grand Total | B17: 10247457 | D17: Grand Total | E17: 10247457 | G17: 10247457
G19: Sum of Quantity
G20: 43608

Sheet Sales
A1: Date | B1: Branch Code | C1: G. Segment Code | D1: Product | E1: Sub category code | F1: Class Code | G1: Quantity | H1: Unit Cost | I1: Unit Price | J1: COGS | K1: Sales | L1: Profit
A2: 40909 | B2: 1 | C2: 1 | D2: Nokia Lumia - 4G | E2: 1 | F2: 1 | G2: 8 | H2: 2034 | I2: 2160 | J2: 16272 | K2: 40053 | L2: 23781
A3: 40909 | B3: 2 | C3: 1 | D3: Samsung Galaxy Note 10.1 | E3: 2 | F3: 2 | G3: 21 | H3: 3582 | I3: 3870 | J3: 75222 | K3: 81270 | L3: 6048
A4: 40909 | B4: 3 | C4: 2 | D4: Samsung Galaxy Note3 (32GB) - 4G | E4: 2 | F4: 1 | G4: 16 | H4: 3978 | I4: 4230 | J4: 63648 | K4: 67680 | L4: 4032
A5: 40909 | B5: 4 | C5: 2 | D5: Samsung Galaxy S3 (16GB) - 3G | E5: 2 | F5: 1 | G5: 23 | H5: 2196 | I5: 2340 | J5: 50508 | K5: 53820 | L5: 3312
A6: 40910 | B6: 5 | C6: 3 | D6: Samsung Galaxy Note3 (32GB) - 4G | E6: 2 | F6: 1 | G6: 22 | H6: 3978 | I6: 4230 | J6: 87516 | K6: 93060 | L6: 5544
A7: 40910 | B7: 6 | C7: 4 | D7: Samsung Galaxy Note3 (32GB) - 4G | E7: 2 | F7: 1 | G7: 13 | H7: 3978 | I7: 4230 | J7: 51714 | K7: 54990 | L7: 3276
A8: 40910 | B8: 2 | C8: 1 | D8: Samsung Galaxy S4 (16GB) - 4G | E8: 2 | F8: 1 | G8: 27 | H8: 3042 | I8: 3240 | J8: 82134 | K8: 87480 | L8: 5346
A9: 40910 | B9: 7 | C9: 3 | D9: Samsung Galaxy Note3 (32GB) - 4G | E9: 2 | F9: 1 | G9: 27 | H9: 3978 | I9: 4230 | J9: 107406 | K9: 114210 | L9: 6804
A10: 40912 | B10: 1 | C10: 1 | D10: Samsung Galaxy Note3 (32GB) - 4G | E10: 2 | F10: 1 | G10: 27 | H10: 3978 | I10: 4230 | J10: 107406 | K10: 114210 | L10: 6804
A11: 40913 | B11: 6 | C11: 4 | D11: iPhone 5S (64GB) | E11: 3 | F11: 1 | G11: 27 | H11: 5832 | I11: 6210 | J11: 157464 | K11: 167670 | L11: 10206
A12: 40913 | B12: 8 | C12: 5 | D12: Samsung Galaxy S3 (16GB) - 3G | E12: 2 | F12: 1 | G12: 27 | H12: 2196 | I12: 2340 | J12: 59292 | K12: 63180 | L12: 3888
A13: 40913 | B13: 9 | C13: 5 | D13: iPhone 5C (16GB) | E13: 3 | F13: 1 | G13: 27 | H13: 3546 | I13: 3780 | J13: 95742 | K13: 102060 | L13: 6318
... A3001: 41912 | B3001: 7 | C3001: 3 | D3001: iPhone 5C (32GB) | E3001: 3 | F3001: 1 | G3001: 6 | H3001: 3546 | I3001: 3780 | J3001: 3978 | K3001: 4230 | L3001: 252

Sheet Code
A1: Category | B1: Code
A2: Furniture | B2: F-101
A3: Office Supplies | B3: O-102
A4: Technology | B4: T-103

Sheet Classes
A1: Class | B1: Code
A2: Smartphones | B2: 1
A3: Tablets | B3: 2

Sheet Sub categories
A1: Sub category | B1: Code
A2: Nokia | B2: 1
A3: Samsung | B3: 2
A4: Apple iPhone | B4: 3
A5: HTC | B5: 4
A6: Sony | B6: 5
A7: Microsoft | B7: 6

Sheet Segments
A1: G. Segment | B1: Code
A2: Alexandria | B2: 1
A3: Delta | B3: 2
A4: Canal | B4: 3
A5: Upper Egypt | B5: 4
A6: G. Cairo | B6: 5

Sheet Branches
A1: Branch | B1: Code
A2: Marasa Matrouh | B2: 1
A3: Alex | B3: 2
A4: Zagazig | B4: 3
A5: Mansoura | B5: 4
A6: Ismailia | B6: 5
A7: Minia | B7: 6
A8: Portsaied | B8: 7
A9: Cairo | B9: 8
A10: Giza | B10: 9
A11: Aswan | B11: 10
